{
  "ApplicationName": "user-service",
  "PackageStructure": "com.example.userservice",
  "Dependencies": [
    "Spring Web",
    "Spring Data JPA",
    "PostgreSQL Driver",
    "Lombok"
  ],
  "RestEndpoints": [
    {
      "Method": "POST",
      "Path": "/users",
      "Description": "Register a new user"
    },
    {
      "Method": "GET",
      "Path": "/users/{id}",
      "Description": "Get user by ID"
    },
    {
      "Method": "GET",
      "Path": "/users/email/{email}",
      "Description": "Get user by email"
    },
    {
      "Method": "PUT",
      "Path": "/users/{id}",
      "Description": "Update user details"
    },
    {
      "Method": "DELETE",
      "Path": "/users/{id}",
      "Description": "Delete a user"
    }
  ],
  "DatabaseConfigurations": {
    "DatabaseType": "PostgreSQL",
    "URL": "jdbc:postgresql://localhost:5432/userdb",
    "Username": "postgres",
    "Password": "postgres"
  },
  "SecurityFeatures": {
    "Authentication": "None (add Spring Security for production)",
    "Authorization": "None (add role-based for production)"
  }
}
